drf_social-1.4.0.dist-info/top_level.txt
drf_social-1.4.0.dist-info/DESCRIPTION.rst
drf_social-1.4.0.dist-info/WHEEL
drf_social-1.4.0.dist-info/METADATA
drf_social-1.4.0.dist-info/metadata.json
drf_social-1.4.0.dist-info/RECORD
drf_social/__init__.py
drf_social/apps.py
drf_social/view.py
drf_social/urls.py
drf_social/models.py
drf_social/admin.py
drf_social/utils.py
drf_social/serializers.py
drf_social/__pycache__/models.cpython-37.pyc
drf_social/__pycache__/helpers.cpython-37.pyc
drf_social/__pycache__/serializers.cpython-37.pyc
drf_social/__pycache__/admin.cpython-37.pyc
drf_social/__pycache__/urls.cpython-37.pyc
drf_social/__pycache__/apps.cpython-37.pyc
drf_social/__pycache__/__init__.cpython-37.pyc
drf_social/__pycache__/view.cpython-37.pyc
drf_social/migrations/__init__.py
drf_social/migrations/0001_initial.py
drf_social/migrations/__pycache__/__init__.cpython-37.pyc
drf_social/migrations/__pycache__/0001_initial.cpython-37.pyc
